deep_inspect/__init__.py
deep_inspect/members_inspector.py
deep_inspect-0.1.1.dist-info/LICENSE
deep_inspect-0.1.1.dist-info/WHEEL
deep_inspect-0.1.1.dist-info/METADATA
deep_inspect-0.1.1.dist-info/RECORD
