Metadata-Version: 2.1
Name: deep-inspect
Version: 0.1.1
Summary: A wrapper for inspect for deeper exploration - all down the directory tree
Home-page: https://github.com/GuyTuval/deep-inspect
License: GNU GPLv3
Author: GuyTuval
Author-email: guytuval@gmail.com
Requires-Python: >=3.6,<4.0
Classifier: Development Status :: 5 - Production/Stable
Classifier: Intended Audience :: Developers
Classifier: License :: OSI Approved :: GNU General Public License v3 (GPLv3)
Classifier: License :: Other/Proprietary License
Classifier: Operating System :: OS Independent
Classifier: Programming Language :: Python
Classifier: Programming Language :: Python :: 3
Classifier: Programming Language :: Python :: 3 :: Only
Classifier: Programming Language :: Python :: 3.6
Classifier: Programming Language :: Python :: 3.7
Classifier: Programming Language :: Python :: 3.8
Classifier: Programming Language :: Python :: 3.9
Classifier: Topic :: Utilities
Classifier: Typing :: Typed
Requires-Dist: pydantic (>=1.7.1,<2.0.0)
Project-URL: Bug Tracker, https://github.com/GuyTuval/deep-inspect/issues
Project-URL: Source, https://github.com/GuyTuval/deep-inspect
